redis/__init__.py
redis/backoff.py
redis/client.py
redis/cluster.py
redis/compat.py
redis/connection.py
redis/crc.py
redis/exceptions.py
redis/key_types.py
redis/lock.py
redis/ocsp.py
redis/retry.py
redis/sentinel.py
redis/typing.py
redis/utils.py
redis/asyncio/__init__.py
redis/asyncio/client.py
redis/asyncio/cluster.py
redis/asyncio/connection.py
redis/asyncio/lock.py
redis/asyncio/parser.py
redis/asyncio/retry.py
redis/asyncio/sentinel.py
redis/asyncio/utils.py
redis/commands/__init__.py
redis/commands/cluster.py
redis/commands/core.py
redis/commands/helpers.py
redis/commands/parser.py
redis/commands/redismodules.py
redis/commands/sentinel.py
redis/commands/bf/__init__.py
redis/commands/bf/commands.py
redis/commands/bf/info.py
redis/commands/graph/__init__.py
redis/commands/graph/commands.py
redis/commands/graph/edge.py
redis/commands/graph/exceptions.py
redis/commands/graph/execution_plan.py
redis/commands/graph/node.py
redis/commands/graph/path.py
redis/commands/graph/query_result.py
redis/commands/json/__init__.py
redis/commands/json/_util.py
redis/commands/json/commands.py
redis/commands/json/decoders.py
redis/commands/json/path.py
redis/commands/search/__init__.py
redis/commands/search/_util.py
redis/commands/search/aggregation.py
redis/commands/search/commands.py
redis/commands/search/document.py
redis/commands/search/field.py
redis/commands/search/indexDefinition.py
redis/commands/search/query.py
redis/commands/search/querystring.py
redis/commands/search/reducers.py
redis/commands/search/result.py
redis/commands/search/suggestion.py
redis/commands/timeseries/__init__.py
redis/commands/timeseries/commands.py
redis/commands/timeseries/info.py
redis/commands/timeseries/utils.py
redis_popper-4.4.9.dist-info/LICENSE
redis_popper-4.4.9.dist-info/METADATA
redis_popper-4.4.9.dist-info/WHEEL
redis_popper-4.4.9.dist-info/top_level.txt
redis_popper-4.4.9.dist-info/RECORD
