Metadata-Version: 2.1
Name: redis-popper
Version: 4.4.9
Summary: Python client for Redis database and key-value store
Home-page: https://github.com/redis/redis-py
Author: Redis Inc.
Author-email: oss@redis.com
License: MIT
Project-URL: Documentation, https://redis.readthedocs.io/en/latest/
Project-URL: Changes, https://github.com/redis/redis-py/releases
Project-URL: Code, https://github.com/redis/redis-py
Project-URL: Issue tracker, https://github.com/redis/redis-py/issues
Keywords: Redis,key-value store,database
Classifier: Development Status :: 5 - Production/Stable
Classifier: Environment :: Console
Classifier: Intended Audience :: Developers
Classifier: License :: OSI Approved :: MIT License
Classifier: Operating System :: OS Independent
Classifier: Programming Language :: Python
Classifier: Programming Language :: Python :: 3
Classifier: Programming Language :: Python :: 3 :: Only
Classifier: Programming Language :: Python :: 3.7
Classifier: Programming Language :: Python :: 3.8
Classifier: Programming Language :: Python :: 3.9
Classifier: Programming Language :: Python :: 3.10
Classifier: Programming Language :: Python :: 3.11
Classifier: Programming Language :: Python :: Implementation :: CPython
Classifier: Programming Language :: Python :: Implementation :: PyPy
Requires-Python: >=3.7
License-File: LICENSE
Requires-Dist: deprecated (>=1.2.3)
Requires-Dist: async-timeout (>=4.0.2)
Requires-Dist: importlib-metadata (>=1.0) ; python_version < "3.8"
Requires-Dist: typing-extensions ; python_version < "3.8"
Provides-Extra: hiredis
Requires-Dist: hiredis (>=1.0.0) ; extra == 'hiredis'
Provides-Extra: ocsp
Requires-Dist: cryptography (>=36.0.1) ; extra == 'ocsp'
Requires-Dist: pyopenssl (==20.0.1) ; extra == 'ocsp'
Requires-Dist: requests (>=2.26.0) ; extra == 'ocsp'
